COPYING.txt
MANIFEST.in
setup.cfg
setup.py
mooltipy/__init__.py
mooltipy/constants.py
mooltipy/mooltipass.py
mooltipy/mooltipass_client.py
mooltipy.egg-info/PKG-INFO
mooltipy.egg-info/SOURCES.txt
mooltipy.egg-info/dependency_links.txt
mooltipy.egg-info/entry_points.txt
mooltipy.egg-info/requires.txt
mooltipy.egg-info/top_level.txt
mooltipy/utilities/__init__.py
mooltipy/utilities/mooltipy_wrapper.py
mooltipy/utilities/mpdata.py
mooltipy/utilities/mpfavorites.py
mooltipy/utilities/mplogin.py
mooltipy/utilities/mpparams.py