Metadata-Version: 1.1
Name: mooltipy
Version: 1.0.0
Summary: Mooltipass command line utilities and development library.
Home-page: https://github.com/osquat/mooltipy
Author: Vic Simeone
Author-email: mooltipy@osquat.com
License: GPLv3+
Keywords: mooltipass
Platform: UNKNOWN
Classifier: Programming Language :: Python
Classifier: Programming Language :: Python :: 2
Classifier: Programming Language :: Python :: 3
Classifier: License :: OSI Approved :: GNU General Public License v3 or later (GPLv3+)
Classifier: Operating System :: POSIX :: Linux
Classifier: Development Status :: 5 - Production/Stable
Classifier: Intended Audience :: Developers
Classifier: Intended Audience :: End Users/Desktop
